qc_opendrive/__init__.py
qc_opendrive/__main__.py
qc_opendrive/base/__init__.py
qc_opendrive/base/models.py
qc_opendrive/base/utils.py
qc_opendrive/basic_preconditions.py
qc_opendrive/checks/__init__.py
qc_opendrive/checks/basic/__init__.py
qc_opendrive/checks/basic/fileheader_is_present.py
qc_opendrive/checks/basic/root_tag_is_opendrive.py
qc_opendrive/checks/basic/valid_xml_document.py
qc_opendrive/checks/basic/version_is_defined.py
qc_opendrive/checks/geometry/__init__.py
qc_opendrive/checks/geometry/road_geometry_parampoly3_arclength_range.py
qc_opendrive/checks/geometry/road_geometry_parampoly3_length_match.py
qc_opendrive/checks/geometry/road_geometry_parampoly3_normalized_range.py
qc_opendrive/checks/geometry/road_lane_border_overlap_with_inner_lanes.py
qc_opendrive/checks/performance/__init__.py
qc_opendrive/checks/performance/performance_avoid_redundant_info.py
qc_opendrive/checks/schema/__init__.py
qc_opendrive/checks/schema/valid_schema.py
qc_opendrive/checks/semantic/__init__.py
qc_opendrive/checks/semantic/junctions_connection_connect_road_no_incoming_road.py
qc_opendrive/checks/semantic/junctions_connection_end_opposite_linkage.py
qc_opendrive/checks/semantic/junctions_connection_one_connection_element.py
qc_opendrive/checks/semantic/junctions_connection_one_link_to_incoming.py
qc_opendrive/checks/semantic/junctions_connection_start_along_linkage.py
qc_opendrive/checks/semantic/road_lane_access_no_mix_of_deny_or_allow.py
qc_opendrive/checks/semantic/road_lane_level_true_one_side.py
qc_opendrive/checks/semantic/road_lane_link_lanes_across_lane_sections.py
qc_opendrive/checks/semantic/road_lane_link_new_lane_appear.py
qc_opendrive/checks/semantic/road_lane_link_zero_width_at_end.py
qc_opendrive/checks/semantic/road_lane_link_zero_width_at_start.py
qc_opendrive/checks/semantic/road_linkage_is_junction_needed.py
qc_opendrive/checks/smoothness/__init__.py
qc_opendrive/checks/smoothness/lane_smoothness_contact_point_no_horizontal_gaps.py
asam_qc_opendrive-1.0.0.dist-info/LICENSE
asam_qc_opendrive-1.0.0.dist-info/LICENSES/3rd_party_terms_and_licenses/Black_LICENSE
asam_qc_opendrive-1.0.0.dist-info/LICENSES/3rd_party_terms_and_licenses/Lxml_LICENSE
asam_qc_opendrive-1.0.0.dist-info/LICENSES/3rd_party_terms_and_licenses/Numpy_LICENSE
asam_qc_opendrive-1.0.0.dist-info/LICENSES/3rd_party_terms_and_licenses/Pyclothoids_LICENSE
asam_qc_opendrive-1.0.0.dist-info/LICENSES/3rd_party_terms_and_licenses/Pytest_LICENSE
asam_qc_opendrive-1.0.0.dist-info/LICENSES/3rd_party_terms_and_licenses/Scipy_LICENSE
asam_qc_opendrive-1.0.0.dist-info/LICENSES/3rd_party_terms_and_licenses/Semver_LICENSE
asam_qc_opendrive-1.0.0.dist-info/LICENSES/3rd_party_terms_and_licenses/Transforms3d_LICENSE
asam_qc_opendrive-1.0.0.dist-info/LICENSES/3rd_party_terms_and_licenses/Xmlschema_LICENSE
asam_qc_opendrive-1.0.0.dist-info/LICENSES/readme.md
asam_qc_opendrive-1.0.0.dist-info/METADATA
asam_qc_opendrive-1.0.0.dist-info/WHEEL
asam_qc_opendrive-1.0.0.dist-info/entry_points.txt
asam_qc_opendrive-1.0.0.dist-info/RECORD
