Metadata-Version: 2.1
Name: asam-qc-opendrive
Version: 1.0.0
Summary: This project implements the OpenDrive Checker for the ASAM Quality Checker project.
License: MPL-2.0
Author: Patrick Abrahão
Author-email: patrick@ivex.ai
Requires-Python: >=3.10,<4.0
Classifier: License :: OSI Approved
Classifier: Programming Language :: Python :: 3
Classifier: Programming Language :: Python :: 3.10
Classifier: Programming Language :: Python :: 3.11
Classifier: Programming Language :: Python :: 3.12
Classifier: Programming Language :: Python :: 3.13
Requires-Dist: asam-qc-baselib (>=1.0.0rc1,<2.0.0)
Requires-Dist: lxml (>=5.2.2,<6.0.0)
Requires-Dist: numpy (>=1.26.0,<2.0.0)
Requires-Dist: pyclothoids (>=0.1.5,<0.2.0)
Requires-Dist: scipy (>=1.14.0,<2.0.0)
Requires-Dist: semver (>=3.0.0,<4.0.0)
Requires-Dist: transforms3d (>=0.4.2,<0.5.0)
Requires-Dist: xmlschema (>=3.3.1,<4.0.0)
